print_torch/__init__.py
print_torch-1.3.dist-info/LICENSE
print_torch-1.3.dist-info/METADATA
print_torch-1.3.dist-info/WHEEL
print_torch-1.3.dist-info/top_level.txt
print_torch-1.3.dist-info/RECORD
