Metadata-Version: 2.1
Name: print-torch
Version: 1.3
Summary: print pytorch tensors and numpy arrays concisely.
Home-page: https://github.com/tjyuyao/print_torch
Author: Yuyao Huang
Author-email: huangyuyao@outlook.com
Project-URL: Bug Tracker, https://github.com/tjyuyao/print_torch/issues
Classifier: Programming Language :: Python :: 3
Classifier: License :: OSI Approved :: MIT License
Classifier: Operating System :: OS Independent
Requires-Python: >=3.7
License-File: LICENSE
Requires-Dist: varname (>=0.8.1)
Requires-Dist: tqdm
